CHANGES.txt
README.txt
setup.py
z3c/__init__.py
z3c.deadlockdebugger.egg-info/PKG-INFO
z3c.deadlockdebugger.egg-info/SOURCES.txt
z3c.deadlockdebugger.egg-info/dependency_links.txt
z3c.deadlockdebugger.egg-info/entry_points.txt
z3c.deadlockdebugger.egg-info/namespace_packages.txt
z3c.deadlockdebugger.egg-info/not-zip-safe
z3c.deadlockdebugger.egg-info/requires.txt
z3c.deadlockdebugger.egg-info/top_level.txt
z3c/deadlockdebugger/__init__.py
z3c/deadlockdebugger/configure.zcml
z3c/deadlockdebugger/threads.py