Metadata-Version: 1.0
Name: z3c.deadlockdebugger
Version: 0.2
Summary: A thread debugger.
Home-page: http://svn.zope.org/z3c.deadlockdebugger
Author: Zope Corporation and Contributors
Author-email: zope3-dev@zope.org
License: ZPL
Platform: UNKNOWN
Classifier: Framework :: Plone
Classifier: Framework :: Zope2
Classifier: Framework :: Zope3
Classifier: Programming Language :: Python
Classifier: Topic :: Software Development :: Libraries :: Python Modules
